agents/__init__.py
agents/base.py
agents/expert_agents.py
agents/factory.py
agents/routing_agent.py
agents/coaching/__init__.py
agents/coaching/advanced_testing.py
agents/coaching/base.py
agents/coaching/feedback_analyzer.py
agents/coaching/life_coach.py
agents/coaching/ml_optimizer.py
agents/coaching/moderator.py
agents/coaching/multi_agent_optimizer.py
agents/coaching/optimization_config.py
agents/coaching/optimizer.py
agents/coaching/optimizer_base.py
agents/individual/__init__.py
agents/individual/content_strategist.py
agents/individual/data_analyst.py
agents/individual/dating_expert.py
agents/individual/developer.py
agents/individual/german_professor.py
agents/individual/researcher.py
agents/individual/seo_expert.py
agents/individual/web_scraper.py
agents/management/__init__.py
agents/management/optimization/__init__.py
agents/management/optimization/ab_testing.py
agents/management/optimization/base.py
agents/management/optimization/feedback.py
agents/management/optimization/ml_optimizer.py
agents/management/optimization/multi_agent.py
agents/management/routing/__init__.py
agents/management/routing/router.py
agents/management/teams/__init__.py
agents/management/teams/base.py
agents/management/teams/coordinator.py
agents/management/teams/business/__init__.py
agents/management/teams/business/general.py
agents/management/teams/language/__init__.py
agents/management/teams/language/general.py
agents/management/teams/relationship/__init__.py
agents/management/teams/relationship/general.py
agents/management/teams/seo/__init__.py
agents/management/teams/seo/ecommerce.py
agents/management/teams/seo/general.py
agents/management/teams/seo/local.py
agents/seo/__init__.py
agents/seo/analyst.py
agents/seo/content.py
agents/seo/expert.py
agents/seo/scraper.py
llms/__init__.py
llms/anthropic_provider.py
llms/base.py
llms/groq_provider.py
llms/openai_provider.py
mcp/__init__.py
mcp/__main__.py
mcp/postgres_agent.py
mcp/run_server.py
mcp/server.py
me2ai_mcp/INSTALLATION.md
me2ai_mcp-0.1.2.dist-info/licenses/LICENSE
me2ai_mcp-0.1.2.dist-info/METADATA
me2ai_mcp-0.1.2.dist-info/WHEEL
me2ai_mcp-0.1.2.dist-info/top_level.txt
me2ai_mcp-0.1.2.dist-info/RECORD
