Metadata-Version: 2.4
Name: me2ai_mcp
Version: 0.1.2
Summary: Enhanced Model Context Protocol Framework for ME2AI with intelligent agent routing
Home-page: https://github.com/achimdehnert/me2ai
Author: ME2AI Team
Author-email: Your Name <your.email@example.com>
License: MIT License
Requires-Python: >=3.8
License-File: LICENSE
Requires-Dist: langchain>=0.1.0
Requires-Dist: langchain-community>=0.0.10
Requires-Dist: openai>=1.0.0
Requires-Dist: groq>=0.3.0
Requires-Dist: anthropic>=0.7.0
Requires-Dist: python-dotenv>=1.0.0
Requires-Dist: duckduckgo-search>=4.1.0
Requires-Dist: beautifulsoup4>=4.12.0
Requires-Dist: requests>=2.31.0
Requires-Dist: wikipedia>=1.4.0
Requires-Dist: arxiv>=2.0.0
Requires-Dist: pydantic>=2.5.0
Requires-Dist: numpy>=1.24.0
Requires-Dist: pandas>=2.1.0
Provides-Extra: dev
Requires-Dist: pytest>=7.0.0; extra == "dev"
Requires-Dist: pytest-asyncio>=0.23.0; extra == "dev"
Requires-Dist: pytest-cov>=4.1.0; extra == "dev"
Requires-Dist: black; extra == "dev"
Requires-Dist: isort; extra == "dev"
Requires-Dist: mypy; extra == "dev"
Dynamic: author
Dynamic: home-page
Dynamic: license-file
Dynamic: requires-python
